config/__init__.py
config/asgi.py
config/settings.py
config/urls.py
config/wsgi.py
core/__init__.py
core/admin.py
core/apps.py
core/cli.py
core/models.py
core/tests.py
core/urls.py
core/views.py
core/migrations/__init__.py
core/templates/das.html
core/templates/login.html
core/templates/table_data.html
msqeditor-1.4.1.dist-info/METADATA
msqeditor-1.4.1.dist-info/WHEEL
msqeditor-1.4.1.dist-info/entry_points.txt
msqeditor-1.4.1.dist-info/top_level.txt
msqeditor-1.4.1.dist-info/RECORD
