Metadata-Version: 2.4
Name: msqeditor
Version: 1.4.1
Summary: msqeditor is a Python-based database management editor built with Django, designed to simplify managing all databases on your VPS through a clean and intuitive web GUI. It allows easy and secure connections from your local machine using SSH tunnels, providing a safe way to administer your databases remotely. Ideal for developers and sysadmins who want a lightweight, customizable tool to manage databases efficiently with enhanced security.
Home-page: https://github.com/mentormisini/dbeditor.git
Author: Mentor Misini
Requires-Dist: asgiref==3.9.1
Requires-Dist: Django==5.2.4
Requires-Dist: mysql-connector-python==9.4.0
Requires-Dist: mysqlclient==2.2.7
Requires-Dist: PyMySQL==1.1.1
Requires-Dist: sqlparse==0.5.3
Requires-Dist: tzdata==2025.2
Dynamic: author
Dynamic: home-page
Dynamic: requires-dist
Dynamic: summary
